MANIFEST.in
README.md
requirements.txt
setup.cfg
setup.py
divesoft_parser/__init__.py
divesoft_parser/cli.py
divesoft_parser/decoder.py
divesoft_parser/utilities.py
divesoft_parser.egg-info/PKG-INFO
divesoft_parser.egg-info/SOURCES.txt
divesoft_parser.egg-info/dependency_links.txt
divesoft_parser.egg-info/entry_points.txt
divesoft_parser.egg-info/requires.txt
divesoft_parser.egg-info/top_level.txt
divesoft_parser/decoders/__init__.py
divesoft_parser/decoders/header.py
divesoft_parser/decoders/record.py
divesoft_parser/decoders/records/__init__.py
divesoft_parser/decoders/records/configuration.py
divesoft_parser/decoders/records/event.py
divesoft_parser/decoders/records/measurement.py
divesoft_parser/decoders/records/point.py
divesoft_parser/decoders/records/status.py
divesoft_parser/models/__init__.py
divesoft_parser/models/dive.py
divesoft_parser/models/enums.py
divesoft_parser/models/records/__init__.py
divesoft_parser/models/records/event.py
divesoft_parser/models/records/measurement.py
divesoft_parser/models/records/point.py
tests/sample.DLF
tests/test_dive_decode.py
tests/test_header_decoder.py
tests/records/__init__.py
tests/records/test_event_decoder.py
tests/records/test_measurement_decoder.py
tests/records/test_point_decoder.py