Metadata-Version: 2.1
Name: divesoft-parser
Version: 0.0.1
Summary: Divesoft Log (DLF) Parser
Home-page: https://github.com/DiveWithDamian/divesoft-parser
Author: Damian Zaremba
Author-email: oss@divewithdamian.eu
License: MIT
Keywords: divesoft dlf
Platform: any
Classifier: Programming Language :: Python :: 3
Classifier: Operating System :: OS Independent
Requires-Python: >=3.9
